proxy_api/__init__.py
proxy_api/api_client.py
test/__init__.py
test/test_api_client.py
proxy_api_package-0.1.1.dist-info/METADATA
proxy_api_package-0.1.1.dist-info/WHEEL
proxy_api_package-0.1.1.dist-info/top_level.txt
proxy_api_package-0.1.1.dist-info/RECORD
