Metadata-Version: 2.2
Name: proxy_api_package
Version: 0.1.1
Summary: A Python client for interacting with a REST API
Home-page: https://github.com/yourusername/proxy_api_package
Author: Antonio Ciorba
Author-email: antoniociorba@outlook.com
Classifier: Programming Language :: Python :: 3
Classifier: License :: OSI Approved :: MIT License
Classifier: Operating System :: OS Independent
Requires-Python: >=3.6
Requires-Dist: requests
Requires-Dist: pandas
Dynamic: author
Dynamic: author-email
Dynamic: classifier
Dynamic: description
Dynamic: description-content-type
Dynamic: home-page
Dynamic: requires-dist
Dynamic: requires-python
Dynamic: summary
